AUTHORS.rst
CONTRIBUTING.rst
HISTORY.rst
LICENSE
MANIFEST.in
README.rst
setup.cfg
setup.py
django_maintenance_window/__init__.py
django_maintenance_window/admin.py
django_maintenance_window/apps.py
django_maintenance_window/middleware.py
django_maintenance_window/models.py
django_maintenance_window/settings.py
django_maintenance_window.egg-info/PKG-INFO
django_maintenance_window.egg-info/SOURCES.txt
django_maintenance_window.egg-info/dependency_links.txt
django_maintenance_window.egg-info/not-zip-safe
django_maintenance_window.egg-info/requires.txt
django_maintenance_window.egg-info/top_level.txt
django_maintenance_window/management/__init__.py
django_maintenance_window/management/commands/__init__.py
django_maintenance_window/management/commands/check_maintenance_mode.py
django_maintenance_window/migrations/0001_initial.py
django_maintenance_window/migrations/0002_auto_20210805_1700.py
django_maintenance_window/migrations/__init__.py
django_maintenance_window/static/css/django_maintenance_window.css
django_maintenance_window/templates/django_maintenance_window/maintenance.html